streamlit_chunked_upload/__init__.py
streamlit_chunked_upload/_models.py
streamlit_chunked_upload/_utils.py
streamlit_chunked_upload/_version.py
streamlit_chunked_upload/frontend/.prettierrc
streamlit_chunked_upload/frontend/package-lock.json
streamlit_chunked_upload/frontend/package.json
streamlit_chunked_upload/frontend/tsconfig.json
streamlit_chunked_upload/frontend/build/asset-manifest.json
streamlit_chunked_upload/frontend/build/bootstrap.min.css
streamlit_chunked_upload/frontend/build/bootstrap.min.css.map
streamlit_chunked_upload/frontend/build/index.html
streamlit_chunked_upload/frontend/build/static/js/main.0363b29b.js
streamlit_chunked_upload/frontend/build/static/js/main.0363b29b.js.LICENSE.txt
streamlit_chunked_upload/frontend/build/static/js/main.0363b29b.js.map
streamlit_chunked_upload/frontend/public/bootstrap.min.css
streamlit_chunked_upload/frontend/public/bootstrap.min.css.map
streamlit_chunked_upload/frontend/public/index.html
streamlit_chunked_upload/frontend/src/FileUploader.tsx
streamlit_chunked_upload/frontend/src/index.tsx
streamlit_chunked_upload/frontend/src/react-app-env.d.ts
streamlit_chunked_upload-1.0.2.dist-info/LICENSE
streamlit_chunked_upload-1.0.2.dist-info/METADATA
streamlit_chunked_upload-1.0.2.dist-info/WHEEL
streamlit_chunked_upload-1.0.2.dist-info/top_level.txt
streamlit_chunked_upload-1.0.2.dist-info/RECORD
