Metadata-Version: 2.2
Name: streamlit-chunked-upload
Version: 1.0.2
Summary: Custom component to perform chunked upload in Streamlit. Based on streamlit-chunked-upload by Ryuya Matsumoto.
Home-page: https://github.com/mirzaahmergull/streamlit-chunked-upload
Author: Ahmer Gull
Author-email: mirzaahmergull@outlook.com
Classifier: Programming Language :: Python :: 3
Classifier: License :: OSI Approved :: MIT License
Classifier: Operating System :: OS Independent
Requires-Python: >=3.7
License-File: LICENSE
Requires-Dist: streamlit>=1.30.0
Provides-Extra: devel
Requires-Dist: wheel; extra == "devel"
Requires-Dist: pytest==7.4.0; extra == "devel"
Requires-Dist: playwright==1.39.0; extra == "devel"
Requires-Dist: requests==2.31.0; extra == "devel"
Requires-Dist: pytest-playwright-snapshot==1.0; extra == "devel"
Requires-Dist: pytest-rerunfailures==12.0; extra == "devel"
